txt_process/__init__.py
txt_process/debug.py
txt_process/format_file.py
txt_process/read_file.py
txt_process/split_file.py
txt_process/my_unittest/__init__.py
txt_process/my_unittest/test_read_file.py
worktools-0.0.2.dist-info/LICENSE
worktools-0.0.2.dist-info/METADATA
worktools-0.0.2.dist-info/WHEEL
worktools-0.0.2.dist-info/top_level.txt
worktools-0.0.2.dist-info/RECORD
